{"Meta":{"Enums":{},"Fields":{"id":"System.Int32","Rank":"System.Int32","Price":"System.Int32","Rarity":"System.Int32","Name":"System.String","Description":"System.String","AbilityId":"System.Int32[]","ConditionParam":"System.Int32"}},"Records":[{"id":"202","Rank":"1","Price":"10","Rarity":"0","Name":"\u30d5\u30a1\u30a4\u30e4\u30fc","Description":"{0}\u6575\u306b{0}\u30c0\u30e1\u30fc\u30b8","AbilityId":["202"],"ConditionParam":"0"},{"id":"203","Rank":"2","Price":"28","Rarity":"0","Name":"\u30e1\u30c6\u30aa","Description":"{0}\u6575\u306b{0}\u30c0\u30e1\u30fc\u30b8","AbilityId":["203"],"ConditionParam":"0"},{"id":"101","Rank":"0","Price":"3","Rarity":"0","Name":"\u30de\u30ca","Description":"\u30de\u30ca+1","AbilityId":["101"],"ConditionParam":"0"},{"id":"102","Rank":"1","Price":"9","Rarity":"0","Name":"\u9b54\u6cd5\u9663","Description":"\u30de\u30ca+2","AbilityId":["102"],"ConditionParam":"0"},{"id":"103","Rank":"2","Price":"27","Rarity":"0","Name":"\u932c\u6210\u9663","Description":"\u30de\u30ca+3","AbilityId":["103"],"ConditionParam":"0"},{"id":"110","Rank":"1","Price":"4","Rarity":"0","Name":"\u932c\u91d1\u8853\u300c\u571f\u300d","Description":"\u30de\u30ca+\u624b\u672d\u3092\u6368\u3066\u305f\u6570","AbilityId":["402","111"],"ConditionParam":"-1"},{"id":"201","Rank":"0","Price":"3","Rarity":"0","Name":"\u706b\u306e\u7c89","Description":"{0}\u6575\u306b{0}\u30c0\u30e1\u30fc\u30b8","AbilityId":["201"],"ConditionParam":"0"}]}